MANIFEST.in
README.md
requirements.txt
setup.py
joker/__init__.py
joker/aligner/__init__.py
joker/aligner/algor.py
joker/aligner/utils.py
joker/aligner/library/__init__.py
joker/aligner/library/align.c
joker/aligner/matrix/ENSUB
joker_aligner.egg-info/PKG-INFO
joker_aligner.egg-info/SOURCES.txt
joker_aligner.egg-info/dependency_links.txt
joker_aligner.egg-info/namespace_packages.txt
joker_aligner.egg-info/not-zip-safe
joker_aligner.egg-info/requires.txt
joker_aligner.egg-info/top_level.txt